{
    "id":  "SWE",
    "name":  "Sweden",
    "display_name":  "Kingdom of Sweden",
    "initial_gdp":  18.0,
    "initial_stability":  0.70,
    "legal_tax_burden":  0.21,
    "fiscal_capacity":  0.60,
    "administrative_efficiency":  0.65,
    "central_control":  0.60,
    "corruption":  0.10,
    "legitimacy":  0.70,
    "military_power":  0.25,
    "threat_perception":  0.20,
    "military_strength":  15.0,
    "budget":  {
                   "administration":  0.22,
                   "military":  0.15,
                   "education":  0.18,
                   "welfare":  0.15,
                   "intelligence":  0.05,
                   "infrastructure":  0.15,
                   "industry":  0.10
               },
    "government_authority":  {
                                 "bureaucratic_compliance":  0.5,
                                 "military_loyalty":  0.5,
                                 "intelligence_capability":  0.5,
                                 "media_control":  0.5,
                                 "bureaucratic_professionalism":  0.65,
                                 "audit_capacity":  0.6,
                                 "leader_isolation":  0.5
                             }
}

